<annotation>
	<folder>data2</folder>
	<filename>photo_04465_51846073144_o.jpg</filename>
	<path>/Users/clement/Desktop/bluelens/data2/photo_04465_51846073144_o.jpg</path>
	<source>
		<database>Unknown</database>
	</source>
	<size>
		<width>4056</width>
		<height>3040</height>
		<depth>3</depth>
	</size>
	<segmented>0</segmented>
	<object>
		<name>cloud</name>
		<pose>Unspecified</pose>
		<truncated>0</truncated>
		<difficult>0</difficult>
		<bndbox>
			<xmin>874</xmin>
			<ymin>579</ymin>
			<xmax>3437</xmax>
			<ymax>2972</ymax>
		</bndbox>
	</object>
	<object>
		<name>water</name>
		<pose>Unspecified</pose>
		<truncated>0</truncated>
		<difficult>0</difficult>
		<bndbox>
			<xmin>493</xmin>
			<ymin>104</ymin>
			<xmax>3105</xmax>
			<ymax>1954</ymax>
		</bndbox>
	</object>
</annotation>
